subcli/__init__.py
subcli/config.py
subcli/get_subtitle.py
subcli/subcli.py
subcli-0.1.5.dist-info/METADATA
subcli-0.1.5.dist-info/WHEEL
subcli-0.1.5.dist-info/entry_points.txt
subcli-0.1.5.dist-info/top_level.txt
subcli-0.1.5.dist-info/RECORD
