Metadata-Version: 2.1
Name: subcli
Version: 0.1.5
Summary: A CLI tool to download subtitles
Home-page: UNKNOWN
Author: yannickRafael
License: UNKNOWN
Platform: UNKNOWN
Classifier: Programming Language :: Python :: 3
Requires-Python: >=3.6
Requires-Dist: click
Requires-Dist: requests
Requires-Dist: beautifulsoup4
Requires-Dist: InquirerPy
